Metadata-Version: 2.1
Name: orfeus
Version: 1.0
Summary: ORFeus: alternative ORF predictor
Author-email: "Mary O. Richardson" <maryrichardson@g.harvard.edu>
Requires-Python: >=3.7
Requires-Dist: numpy (>=1.21.5)
Requires-Dist: pandas (>=1.3.5)
Requires-Dist: scipy (>=1.7.3)
Requires-Dist: matplotlib (>=3.5.3)
